README.md
setup.py
cellsaw/__init__.py
cellsaw/__version__.py
cellsaw/_version.py
cellsaw/draw.py
cellsaw/preprocess.py
cellsaw/util.py
cellsaw.egg-info/PKG-INFO
cellsaw.egg-info/SOURCES.txt
cellsaw.egg-info/dependency_links.txt
cellsaw.egg-info/requires.txt
cellsaw.egg-info/top_level.txt
cellsaw/annotate/__init__.py
cellsaw/annotate/annotators.py
cellsaw/annotate/draw.py
cellsaw/io_utils/__init__.py
cellsaw/io_utils/loadadata.py
cellsaw/merge/__init__.py
cellsaw/merge/eval.py
cellsaw/merge/hungarianEM.py
cellsaw/merge/mergehelpers.py
cellsaw/merge/diffusion/__init__.py
cellsaw/merge/diffusion/kernel.py
cellsaw/similarity/__init__.py
cellsaw/similarity/measures.py
lucy/adatas.py
lucy/draw.py
lucy/embed.py
lucy/load.py
lucy/merge.py
lucy/score.py