Metadata-Version: 2.1
Name: cellsaw
Version: 0.0.58
Summary: match clusters of sincle cell experiments with the Hungarian
Home-page: https://github.com/smautner/cellsaw
Author: Stefan Mautner
Author-email: myl4stn4m3@cs.uni-freiburg.de
License: LICENSE
Platform: UNKNOWN
